<annotation>
	<folder>images_mask</folder>
	<filename>maksssksksss95.jpg</filename>
	<path>/home/achrafnvl/Escritorio/PersonDetect/images_mask/maksssksksss95.jpg</path>
	<source>
		<database>Unknown</database>
	</source>
	<size>
		<width>301</width>
		<height>400</height>
		<depth>3</depth>
	</size>
	<segmented>0</segmented>
	<object>
		<name>no_mask</name>
		<pose>Unspecified</pose>
		<truncated>1</truncated>
		<difficult>0</difficult>
		<bndbox>
			<xmin>45</xmin>
			<ymin>267</ymin>
			<xmax>161</xmax>
			<ymax>400</ymax>
		</bndbox>
	</object>
</annotation>
